nr/__init__.py
nr/pylang/__init__.py
nr/pylang/utils/__init__.py
nr/pylang/utils/classdef.py
nr/pylang/utils/funcdef.py
nr/pylang/utils/funcdef_test.py
nr/pylang/utils/module.py
nr/pylang/utils/py.typed
nr/pylang/utils/singletons.py
nr/pylang/utils/typing.py
nr.pylang.utils-0.1.3.dist-info/LICENSE.txt
nr.pylang.utils-0.1.3.dist-info/METADATA
nr.pylang.utils-0.1.3.dist-info/WHEEL
nr.pylang.utils-0.1.3.dist-info/top_level.txt
nr.pylang.utils-0.1.3.dist-info/RECORD
